easysense/__init__.py
easysense/cli.py
easysense/config.yaml
easysense/easysense.py
easysense/main.py
easysense/sensors/.example/main.py
easysense/sensors/.example/requirements.txt
easysense-1.0.11.dist-info/METADATA
easysense-1.0.11.dist-info/WHEEL
easysense-1.0.11.dist-info/entry_points.txt
easysense-1.0.11.dist-info/licenses/LICENSE
easysense-1.0.11.dist-info/RECORD
