Metadata-Version: 2.3
Name: easysense
Version: 1.0.11
Summary: A CLI tool providing pre-written sensor implementations for Wiresense, designed to simplify sensor integration and data collection.
Project-URL: Homepage, https://github.com/Saladrian/easysense.py#readme
Project-URL: Issues, https://github.com/Saladrian/easysense.py/issues
Project-URL: Available Sensors, https://github.com/Saladrian/easysense.py-sensors
Author: Saladrian
License-File: LICENSE
Classifier: License :: OSI Approved :: MIT License
Classifier: Operating System :: OS Independent
Classifier: Programming Language :: Python :: 3
Requires-Python: >=3.8
Requires-Dist: adafruit-blinka>=8.41.2
Requires-Dist: pyyaml>=6.0.1
Requires-Dist: wiresense>=1.0.2
